Workbook

Sheet Resumo
A1: Resumo financeiro
A2: Mês de referência (altere a data): | B2: 46296 | C2: =EOMONTH(B2,0)
F3: Gastos por categoria | G3: Total | H3: % do mês
A4: Ganhos do mês | B4: =SUMIFS('Lançamentos'!$E:$E,'Lançamentos'!$D:$D,"Ganho",'Lançamentos'!$A:$A,">="&$B$2,'Lançamentos'!$A:$A,"<="&$C$2) | F4: Moradia | G4: =SUMIFS('Lançamentos'!$E:$E,'Lançamentos'!$D:$D,"Gasto",'Lançamentos'!$A:$A,">="&$B$2,'Lançamentos'!$A:$A,"<="&$C$2,'Lançamentos'!$C:$C,F4) | H4: =IF($B$5=0,0,G4/$B$5)
A5: Gastos do mês | B5: =SUMIFS('Lançamentos'!$E:$E,'Lançamentos'!$D:$D,"Gasto",'Lançamentos'!$A:$A,">="&$B$2,'Lançamentos'!$A:$A,"<="&$C$2) | F5: Alimentação | G5: =SUMIFS('Lançamentos'!$E:$E,'Lançamentos'!$D:$D,"Gasto",'Lançamentos'!$A:$A,">="&$B$2,'Lançamentos'!$A:$A,"<="&$C$2,'Lançamentos'!$C:$C,F5) | H5: =IF($B$5=0,0,G5/$B$5)
A6: Saldo do mês | B6: =B4-B5 | F6: Mercado | G6: =SUMIFS('Lançamentos'!$E:$E,'Lançamentos'!$D:$D,"Gasto",'Lançamentos'!$A:$A,">="&$B$2,'Lançamentos'!$A:$A,"<="&$C$2,'Lançamentos'!$C:$C,F6) | H6: =IF($B$5=0,0,G6/$B$5)
A7: Taxa de poupança | B7: =IF(B4=0,0,B6/B4) | F7: Transporte | G7: =SUMIFS('Lançamentos'!$E:$E,'Lançamentos'!$D:$D,"Gasto",'Lançamentos'!$A:$A,">="&$B$2,'Lançamentos'!$A:$A,"<="&$C$2,'Lançamentos'!$C:$C,F7) | H7: =IF($B$5=0,0,G7/$B$5)
A8: Dívidas em aberto | B8: =SUM('Dívidas'!$C:$C) | F8: Contas da casa | G8: =SUMIFS('Lançamentos'!$E:$E,'Lançamentos'!$D:$D,"Gasto",'Lançamentos'!$A:$A,">="&$B$2,'Lançamentos'!$A:$A,"<="&$C$2,'Lançamentos'!$C:$C,F8) | H8: =IF($B$5=0,0,G8/$B$5)
A9: Juros das dívidas por mês | B9: =SUM('Dívidas'!$I:$I) | F9: Saúde | G9: =SUMIFS('Lançamentos'!$E:$E,'Lançamentos'!$D:$D,"Gasto",'Lançamentos'!$A:$A,">="&$B$2,'Lançamentos'!$A:$A,"<="&$C$2,'Lançamentos'!$C:$C,F9) | H9: =IF($B$5=0,0,G9/$B$5)
A10: Parcelas de dívidas por mês | B10: =SUM('Dívidas'!$F:$F) | F10: Educação | G10: =SUMIFS('Lançamentos'!$E:$E,'Lançamentos'!$D:$D,"Gasto",'Lançamentos'!$A:$A,">="&$B$2,'Lançamentos'!$A:$A,"<="&$C$2,'Lançamentos'!$C:$C,F10) | H10: =IF($B$5=0,0,G10/$B$5)
A11: Comprometimento da renda | B11: =IF(B4=0,0,B10/B4) | F11: Lazer | G11: =SUMIFS('Lançamentos'!$E:$E,'Lançamentos'!$D:$D,"Gasto",'Lançamentos'!$A:$A,">="&$B$2,'Lançamentos'!$A:$A,"<="&$C$2,'Lançamentos'!$C:$C,F11) | H11: =IF($B$5=0,0,G11/$B$5)
A12: Patrimônio investido | B12: =SUMIFS(Investimentos!$E:$E,Investimentos!$C:$C,"Ativo") | F12: Assinaturas | G12: =SUMIFS('Lançamentos'!$E:$E,'Lançamentos'!$D:$D,"Gasto",'Lançamentos'!$A:$A,">="&$B$2,'Lançamentos'!$A:$A,"<="&$C$2,'Lançamentos'!$C:$C,F12) | H12: =IF($B$5=0,0,G12/$B$5)
A13: Aportes planejados por mês | B13: =SUM(Investimentos!$G:$G) | F13: Vestuário | G13: =SUMIFS('Lançamentos'!$E:$E,'Lançamentos'!$D:$D,"Gasto",'Lançamentos'!$A:$A,">="&$B$2,'Lançamentos'!$A:$A,"<="&$C$2,'Lançamentos'!$C:$C,F13) | H13: =IF($B$5=0,0,G13/$B$5)
F14: Pagamento de dívidas | G14: =SUMIFS('Lançamentos'!$E:$E,'Lançamentos'!$D:$D,"Gasto",'Lançamentos'!$A:$A,">="&$B$2,'Lançamentos'!$A:$A,"<="&$C$2,'Lançamentos'!$C:$C,F14) | H14: =IF($B$5=0,0,G14/$B$5)
A15: Últimos 12 meses | F15: Investimentos | G15: =SUMIFS('Lançamentos'!$E:$E,'Lançamentos'!$D:$D,"Gasto",'Lançamentos'!$A:$A,">="&$B$2,'Lançamentos'!$A:$A,"<="&$C$2,'Lançamentos'!$C:$C,F15) | H15: =IF($B$5=0,0,G15/$B$5)
A16: Mês | B16: Ganhos | C16: Gastos | D16: Saldo | F16: Outros gastos | G16: =SUMIFS('Lançamentos'!$E:$E,'Lançamentos'!$D:$D,"Gasto",'Lançamentos'!$A:$A,">="&$B$2,'Lançamentos'!$A:$A,"<="&$C$2,'Lançamentos'!$C:$C,F16) | H16: =IF($B$5=0,0,G16/$B$5)
A17: =EDATE($B$2,-11) | B17: =SUMIFS('Lançamentos'!$E:$E,'Lançamentos'!$D:$D,"Ganho",'Lançamentos'!$A:$A,">="&$A17,'Lançamentos'!$A:$A,"<="&EOMONTH($A17,0)) | C17: =SUMIFS('Lançamentos'!$E:$E,'Lançamentos'!$D:$D,"Gasto",'Lançamentos'!$A:$A,">="&$A17,'Lançamentos'!$A:$A,"<="&EOMONTH($A17,0)) | D17: =B17-C17
A18: =EDATE($B$2,-10) | B18: =SUMIFS('Lançamentos'!$E:$E,'Lançamentos'!$D:$D,"Ganho",'Lançamentos'!$A:$A,">="&$A18,'Lançamentos'!$A:$A,"<="&EOMONTH($A18,0)) | C18: =SUMIFS('Lançamentos'!$E:$E,'Lançamentos'!$D:$D,"Gasto",'Lançamentos'!$A:$A,">="&$A18,'Lançamentos'!$A:$A,"<="&EOMONTH($A18,0)) | D18: =B18-C18
A19: =EDATE($B$2,-9) | B19: =SUMIFS('Lançamentos'!$E:$E,'Lançamentos'!$D:$D,"Ganho",'Lançamentos'!$A:$A,">="&$A19,'Lançamentos'!$A:$A,"<="&EOMONTH($A19,0)) | C19: =SUMIFS('Lançamentos'!$E:$E,'Lançamentos'!$D:$D,"Gasto",'Lançamentos'!$A:$A,">="&$A19,'Lançamentos'!$A:$A,"<="&EOMONTH($A19,0)) | D19: =B19-C19
A20: =EDATE($B$2,-8) | B20: =SUMIFS('Lançamentos'!$E:$E,'Lançamentos'!$D:$D,"Ganho",'Lançamentos'!$A:$A,">="&$A20,'Lançamentos'!$A:$A,"<="&EOMONTH($A20,0)) | C20: =SUMIFS('Lançamentos'!$E:$E,'Lançamentos'!$D:$D,"Gasto",'Lançamentos'!$A:$A,">="&$A20,'Lançamentos'!$A:$A,"<="&EOMONTH($A20,0)) | D20: =B20-C20
A21: =EDATE($B$2,-7) | B21: =SUMIFS('Lançamentos'!$E:$E,'Lançamentos'!$D:$D,"Ganho",'Lançamentos'!$A:$A,">="&$A21,'Lançamentos'!$A:$A,"<="&EOMONTH($A21,0)) | C21: =SUMIFS('Lançamentos'!$E:$E,'Lançamentos'!$D:$D,"Gasto",'Lançamentos'!$A:$A,">="&$A21,'Lançamentos'!$A:$A,"<="&EOMONTH($A21,0)) | D21: =B21-C21
A22: =EDATE($B$2,-6) | B22: =SUMIFS('Lançamentos'!$E:$E,'Lançamentos'!$D:$D,"Ganho",'Lançamentos'!$A:$A,">="&$A22,'Lançamentos'!$A:$A,"<="&EOMONTH($A22,0)) | C22: =SUMIFS('Lançamentos'!$E:$E,'Lançamentos'!$D:$D,"Gasto",'Lançamentos'!$A:$A,">="&$A22,'Lançamentos'!$A:$A,"<="&EOMONTH($A22,0)) | D22: =B22-C22
A23: =EDATE($B$2,-5) | B23: =SUMIFS('Lançamentos'!$E:$E,'Lançamentos'!$D:$D,"Ganho",'Lançamentos'!$A:$A,">="&$A23,'Lançamentos'!$A:$A,"<="&EOMONTH($A23,0)) | C23: =SUMIFS('Lançamentos'!$E:$E,'Lançamentos'!$D:$D,"Gasto",'Lançamentos'!$A:$A,">="&$A23,'Lançamentos'!$A:$A,"<="&EOMONTH($A23,0)) | D23: =B23-C23
A24: =EDATE($B$2,-4) | B24: =SUMIFS('Lançamentos'!$E:$E,'Lançamentos'!$D:$D,"Ganho",'Lançamentos'!$A:$A,">="&$A24,'Lançamentos'!$A:$A,"<="&EOMONTH($A24,0)) | C24: =SUMIFS('Lançamentos'!$E:$E,'Lançamentos'!$D:$D,"Gasto",'Lançamentos'!$A:$A,">="&$A24,'Lançamentos'!$A:$A,"<="&EOMONTH($A24,0)) | D24: =B24-C24
A25: =EDATE($B$2,-3) | B25: =SUMIFS('Lançamentos'!$E:$E,'Lançamentos'!$D:$D,"Ganho",'Lançamentos'!$A:$A,">="&$A25,'Lançamentos'!$A:$A,"<="&EOMONTH($A25,0)) | C25: =SUMIFS('Lançamentos'!$E:$E,'Lançamentos'!$D:$D,"Gasto",'Lançamentos'!$A:$A,">="&$A25,'Lançamentos'!$A:$A,"<="&EOMONTH($A25,0)) | D25: =B25-C25
A26: =EDATE($B$2,-2) | B26: =SUMIFS('Lançamentos'!$E:$E,'Lançamentos'!$D:$D,"Ganho",'Lançamentos'!$A:$A,">="&$A26,'Lançamentos'!$A:$A,"<="&EOMONTH($A26,0)) | C26: =SUMIFS('Lançamentos'!$E:$E,'Lançamentos'!$D:$D,"Gasto",'Lançamentos'!$A:$A,">="&$A26,'Lançamentos'!$A:$A,"<="&EOMONTH($A26,0)) | D26: =B26-C26
A27: =EDATE($B$2,-1) | B27: =SUMIFS('Lançamentos'!$E:$E,'Lançamentos'!$D:$D,"Ganho",'Lançamentos'!$A:$A,">="&$A27,'Lançamentos'!$A:$A,"<="&EOMONTH($A27,0)) | C27: =SUMIFS('Lançamentos'!$E:$E,'Lançamentos'!$D:$D,"Gasto",'Lançamentos'!$A:$A,">="&$A27,'Lançamentos'!$A:$A,"<="&EOMONTH($A27,0)) | D27: =B27-C27
A28: =EDATE($B$2,0) | B28: =SUMIFS('Lançamentos'!$E:$E,'Lançamentos'!$D:$D,"Ganho",'Lançamentos'!$A:$A,">="&$A28,'Lançamentos'!$A:$A,"<="&EOMONTH($A28,0)) | C28: =SUMIFS('Lançamentos'!$E:$E,'Lançamentos'!$D:$D,"Gasto",'Lançamentos'!$A:$A,">="&$A28,'Lançamentos'!$A:$A,"<="&EOMONTH($A28,0)) | D28: =B28-C28
A30: Dica: registre tudo na aba Lançamentos. Este resumo, as fórmulas das dívidas e dos investimentos se atualizam sozinhos.

Sheet Lançamentos
A1: Data | B1: Descrição | C1: Categoria | D1: Tipo | E1: Valor | F1: Forma de pagamento

Sheet Dívidas
A1: Credor | B1: Tipo | C1: Saldo devedor | D1: Juros a.m. (%) | E1: Juros a.a. (equiv.) | F1: Parcela mensal | G1: Dia venc. | H1: Em atraso | I1: Juros gerados/mês | J1: Observações
E2: =IF(D2="","",(1+D2/100)^12-1) | I2: =IF(C2="","",C2*D2/100)
E3: =IF(D3="","",(1+D3/100)^12-1) | I3: =IF(C3="","",C3*D3/100)
E4: =IF(D4="","",(1+D4/100)^12-1) | I4: =IF(C4="","",C4*D4/100)
E5: =IF(D5="","",(1+D5/100)^12-1) | I5: =IF(C5="","",C5*D5/100)
E6: =IF(D6="","",(1+D6/100)^12-1) | I6: =IF(C6="","",C6*D6/100)
E7: =IF(D7="","",(1+D7/100)^12-1) | I7: =IF(C7="","",C7*D7/100)
E8: =IF(D8="","",(1+D8/100)^12-1) | I8: =IF(C8="","",C8*D8/100)
E9: =IF(D9="","",(1+D9/100)^12-1) | I9: =IF(C9="","",C9*D9/100)
E10: =IF(D10="","",(1+D10/100)^12-1) | I10: =IF(C10="","",C10*D10/100)
E11: =IF(D11="","",(1+D11/100)^12-1) | I11: =IF(C11="","",C11*D11/100)
E12: =IF(D12="","",(1+D12/100)^12-1) | I12: =IF(C12="","",C12*D12/100)
E13: =IF(D13="","",(1+D13/100)^12-1) | I13: =IF(C13="","",C13*D13/100)
... E51: =IF(D51="","",(1+D51/100)^12-1) | I51: =IF(C51="","",C51*D51/100)

Sheet Investimentos
A1: Nome | B1: Tipo | C1: Situação | D1: Valor aplicado | E1: Valor atual | F1: Rendimento | G1: Aporte mensal | H1: Meta | I1: Progresso | J1: Rent. esperada (% a.a.) | K1: Início | L1: Observações
F2: =IF(A2="","",E2-D2) | I2: =IF(OR(H2="",H2=0),"",MIN(1,E2/H2))
F3: =IF(A3="","",E3-D3) | I3: =IF(OR(H3="",H3=0),"",MIN(1,E3/H3))
F4: =IF(A4="","",E4-D4) | I4: =IF(OR(H4="",H4=0),"",MIN(1,E4/H4))
F5: =IF(A5="","",E5-D5) | I5: =IF(OR(H5="",H5=0),"",MIN(1,E5/H5))
F6: =IF(A6="","",E6-D6) | I6: =IF(OR(H6="",H6=0),"",MIN(1,E6/H6))
F7: =IF(A7="","",E7-D7) | I7: =IF(OR(H7="",H7=0),"",MIN(1,E7/H7))
F8: =IF(A8="","",E8-D8) | I8: =IF(OR(H8="",H8=0),"",MIN(1,E8/H8))
F9: =IF(A9="","",E9-D9) | I9: =IF(OR(H9="",H9=0),"",MIN(1,E9/H9))
F10: =IF(A10="","",E10-D10) | I10: =IF(OR(H10="",H10=0),"",MIN(1,E10/H10))
F11: =IF(A11="","",E11-D11) | I11: =IF(OR(H11="",H11=0),"",MIN(1,E11/H11))
F12: =IF(A12="","",E12-D12) | I12: =IF(OR(H12="",H12=0),"",MIN(1,E12/H12))
F13: =IF(A13="","",E13-D13) | I13: =IF(OR(H13="",H13=0),"",MIN(1,E13/H13))
... F51: =IF(A51="","",E51-D51) | I51: =IF(OR(H51="",H51=0),"",MIN(1,E51/H51))

Sheet Listas
A1: Tipos | B1: Categorias | C1: Formas de pagamento | D1: Tipos de dívida | E1: Tipos de investimento | F1: Situação | G1: Sim/Não
A2: Ganho | B2: Moradia | C2: Pix | D2: Cartão de crédito | E2: Reserva de emergência | F2: Ativo | G2: Sim
A3: Gasto | B3: Alimentação | C3: Débito | D3: Cheque especial | E3: Tesouro Direto | F3: Planejado | G3: Não
B4: Mercado | C4: Cartão de crédito | D4: Empréstimo pessoal | E4: CDB
B5: Transporte | C5: Dinheiro | D5: Consignado | E5: LCI / LCA
B6: Contas da casa | C6: Boleto | D6: Financiamento | E6: Ações
B7: Saúde | C7: Transferência | D7: Crediário / loja | E7: Fundos imobiliários
B8: Educação | D8: Outra | E8: ETFs
B9: Lazer | E9: Previdência
B10: Assinaturas | E10: Criptoativos
B11: Vestuário | E11: Outro
B12: Pagamento de dívidas
B13: Investimentos
B14: Outros gastos
B15: Salário
B16: Freelance / bico
B17: Vendas
B18: Benefícios
B19: Rendimentos
B20: Outras receitas
